README.md
setup.py
py_ttern.egg-info/PKG-INFO
py_ttern.egg-info/SOURCES.txt
py_ttern.egg-info/dependency_links.txt
py_ttern.egg-info/requires.txt
py_ttern.egg-info/top_level.txt
pyttern/__init__.py
pyttern/core.py
pyttern/pyttern.py